null_lens/__init__.py
null_lens/client.py
null_lens-1.0.2.dist-info/METADATA
null_lens-1.0.2.dist-info/WHEEL
null_lens-1.0.2.dist-info/top_level.txt
null_lens-1.0.2.dist-info/RECORD
