Metadata-Version: 2.4
Name: null-lens
Version: 1.0.2
Summary: The missing protocol between user requests and AI actions — standardized intent parsing for every AI system.
Author-email: Null Technologies <support@null-core.ai>
License: MIT
Project-URL: Homepage, https://null-core.ai
Project-URL: Repository, https://github.com/null-core-ai/null-lens
Keywords: AI,intent,parser,standardization,sdk
Requires-Python: >=3.8
Requires-Dist: requests
